objectmodel/__init__.py
objectmodel/_version.py
objectmodel/base.py
objectmodel/errors.py
objectmodel/fields.py
objectmodel/model.py
objectmodel/validation.py
objectmodel-0.2.dist-info/LICENSE
objectmodel-0.2.dist-info/METADATA
objectmodel-0.2.dist-info/WHEEL
objectmodel-0.2.dist-info/top_level.txt
objectmodel-0.2.dist-info/RECORD
