Metadata-Version: 2.1
Name: objectmodel
Version: 0.2
Summary: Python typed object schema validation
Home-page: https://github.com/bshishov/objectmodel
Author: Boris Shishov
Author-email: borisshishov@gmail.com
License: MIT
Platform: UNKNOWN
Classifier: Development Status :: 2 - Pre-Alpha
Classifier: License :: OSI Approved :: MIT License
Classifier: Intended Audience :: Developers
Classifier: Programming Language :: Python :: 3
Classifier: Programming Language :: Python :: 3.7
Classifier: Programming Language :: Python :: 3.8
Classifier: Operating System :: OS Independent
Classifier: Topic :: Software Development :: Libraries
Requires-Python: >=3.7
Provides-Extra: dev
Requires-Dist: pytest ; extra == 'dev'
